odoo10_addon_web_widget_domain_v11-10.0.1.0.1-py2.7-nspkg.pth
odoo/addons/web_widget_domain_v11/README.rst
odoo/addons/web_widget_domain_v11/__init__.py
odoo/addons/web_widget_domain_v11/__manifest__.py
odoo/addons/web_widget_domain_v11/static/description/icon.png
odoo/addons/web_widget_domain_v11/static/src/copied-css/domain_selector.less
odoo/addons/web_widget_domain_v11/static/src/copied-css/model_field_selector.less
odoo/addons/web_widget_domain_v11/static/src/copied-js/domain_selector.js
odoo/addons/web_widget_domain_v11/static/src/copied-js/domain_selector_dialog.js
odoo/addons/web_widget_domain_v11/static/src/copied-js/domain_utils.js
odoo/addons/web_widget_domain_v11/static/src/copied-js/model_field_selector.js
odoo/addons/web_widget_domain_v11/static/src/copied-xml/templates.xml
odoo/addons/web_widget_domain_v11/static/src/js/domain_field.js
odoo/addons/web_widget_domain_v11/templates/assets.xml
odoo/addons/web_widget_domain_v11/views/ir_filters.xml
odoo10_addon_web_widget_domain_v11-10.0.1.0.1.dist-info/DESCRIPTION.rst
odoo10_addon_web_widget_domain_v11-10.0.1.0.1.dist-info/METADATA
odoo10_addon_web_widget_domain_v11-10.0.1.0.1.dist-info/RECORD
odoo10_addon_web_widget_domain_v11-10.0.1.0.1.dist-info/WHEEL
odoo10_addon_web_widget_domain_v11-10.0.1.0.1.dist-info/metadata.json
odoo10_addon_web_widget_domain_v11-10.0.1.0.1.dist-info/namespace_packages.txt
odoo10_addon_web_widget_domain_v11-10.0.1.0.1.dist-info/top_level.txt
